config_formatter.py
config_formatter-1.2.0.dist-info/LICENSE
config_formatter-1.2.0.dist-info/METADATA
config_formatter-1.2.0.dist-info/WHEEL
config_formatter-1.2.0.dist-info/top_level.txt
config_formatter-1.2.0.dist-info/RECORD
