Metadata-Version: 2.1
Name: config-formatter
Version: 1.2.0
Summary: An automatic formatter for .ini and .cfg configuration files
Home-page: https://github.com/Delgan/config-formatter
Author: Delgan
Author-email: delgan.py@gmail.com
License: MIT
Project-URL: Changelog, https://github.com/Delgan/config-formatter/blob/main/CHANGELOG.md
Keywords: config,formatter,ini,cfg,configuration,configparser
Classifier: Development Status :: 5 - Production/Stable
Classifier: Topic :: Software Development :: Libraries :: Python Modules
Classifier: Topic :: Software Development :: Quality Assurance
Classifier: Intended Audience :: Developers
Classifier: License :: OSI Approved :: MIT License
Classifier: Operating System :: OS Independent
Classifier: Programming Language :: Python
Classifier: Programming Language :: Python :: 3
Classifier: Programming Language :: Python :: 3.6
Classifier: Programming Language :: Python :: 3.7
Classifier: Programming Language :: Python :: 3.8
Classifier: Programming Language :: Python :: 3.9
Classifier: Programming Language :: Python :: 3.10
Classifier: Programming Language :: Python :: 3 :: Only
Classifier: Programming Language :: Python :: Implementation :: CPython
Classifier: Programming Language :: Python :: Implementation :: PyPy
Requires-Python: >=3.6
License-File: LICENSE
Requires-Dist: configupdater >=3.0
Provides-Extra: dev
Requires-Dist: pre-commit >=2.17.0 ; extra == 'dev'
Requires-Dist: pytest >=6.0.0 ; extra == 'dev'
